[{"target": "билл", "type": "suit", "source": "расследование"}, {"target": "подест", "type": "suit", "source": "подест"}, {"target": "рынок", "type": "suit", "source": "валюта"}, {"target": "фбр", "type": "suit", "source": "расследование"}, {"target": "подест", "type": "suit", "source": "ассанж"}, {"target": "рынок", "type": "suit", "source": "экономист"}, {"target": "билл", "type": "suit", "source": "поездка"}, {"target": "clinton", "type": "suit", "source": "фбр"}, {"target": "фбр", "type": "suit", "source": "clinton"}, {"target": "валюта", "type": "suit", "source": "экономист"}, {"target": "расследование", "type": "suit", "source": "clinton"}, {"target": "билл", "type": "suit", "source": "пинчук"}, {"target": "фбр", "type": "suit", "source": "фбр"}, {"target": "расследование", "type": "suit", "source": "фбр"}, {"target": "билл", "type": "suit", "source": "фбр"}]