[{"target": "sunday", "type": "suit", "source": "фигуристка"}, {"target": "экспорт", "type": "suit", "source": "немец"}, {"target": "регулирование", "type": "suit", "source": "сенсация"}, {"target": "протест", "type": "suit", "source": "турция"}, {"target": "протест", "type": "suit", "source": "нато"}, {"target": "нато", "type": "suit", "source": "нато"}, {"target": "нато", "type": "suit", "source": "протест"}, {"target": "сенсация", "type": "suit", "source": "индианаполис"}, {"target": "турция", "type": "suit", "source": "сенсация"}, {"target": "sunday", "type": "suit", "source": "дэррок"}, {"target": "протест", "type": "suit", "source": "индианаполис"}, {"target": "нато", "type": "suit", "source": "сектор"}, {"target": "нато", "type": "suit", "source": "турция"}, {"target": "регулирование", "type": "suit", "source": "сектор"}, {"target": "протест", "type": "suit", "source": "экспорт"}]